simple_metrics/__init__.py
simple_metrics/cli.py
simple_metrics/export.py
simple_metrics/fetch.py
simple_metrics-0.1.7.dist-info/METADATA
simple_metrics-0.1.7.dist-info/RECORD
simple_metrics-0.1.7.dist-info/WHEEL
simple_metrics-0.1.7.dist-info/entry_points.txt
simple_metrics-0.1.7.dist-info/top_level.txt
