Metadata-Version: 2.1
Name: simple-metrics
Version: 0.1.7
Summary: Simple portfolio metrics for Robinhood
Home-page: https://github.com/westonplatter/simple_metrics/
Author: Weston Platter
Author-email: westonplatter@gmail.com
License: UNKNOWN
Platform: UNKNOWN
Requires-Dist: click
Requires-Dist: fast-arrow (==0.0.3)
